MANIFEST.in
README.txt
requirements.txt
setup.py
tox.ini
db_util.egg-info/PKG-INFO
db_util.egg-info/SOURCES.txt
db_util.egg-info/dependency_links.txt
db_util.egg-info/requires.txt
db_util.egg-info/top_level.txt
dbutil/__init__.py
dbutil/dbUtil.py
dbutil/constants/__init__.py
dbutil/constants/constants.py
dbutil/sql/create_database.ddl
dbutil/sql/create_table.ddl
dbutil/sql/create_tw_user_table.ddl
dbutil/sql/delete_msg.sql
dbutil/sql/drop_database.ddl
dbutil/sql/drop_table.ddl
dbutil/sql/insert_msg.sql
dbutil/sql/insert_tw_contents.sql
dbutil/sql/selectUserInfo.sql
dbutil/sql/selectUserInfo_not_exist.sql
dbutil/sql/select_all_msg.sql
dbutil/sql/select_all_tables.sql
dbutil/sql/select_all_tables_manage.sql
dbutil/sql/select_all_tables_no_table.sql
dbutil/sql/select_all_tables_one_table.sql
dbutil/sql/select_msg_by_keyword.sql
dbutil/sql/select_single_msg.sql
dbutil/tests/__init__.py
dbutil/tests/test_dbUtil.py
dbutil/util/__init__.py
dbutil/util/deco.py